flywheel_bids/__init__.py
flywheel_bids/curate_bids.py
flywheel_bids/export_bids.py
flywheel_bids/upload_bids.py
flywheel_bids/flywheel_bids_app_toolkit/__init__.py
flywheel_bids/flywheel_bids_app_toolkit/autoupdate.py
flywheel_bids/flywheel_bids_app_toolkit/commands.py
flywheel_bids/flywheel_bids_app_toolkit/compression.py
flywheel_bids/flywheel_bids_app_toolkit/context.py
flywheel_bids/flywheel_bids_app_toolkit/docker_build_utils.py
flywheel_bids/flywheel_bids_app_toolkit/hpc_utils.py
flywheel_bids/flywheel_bids_app_toolkit/prep.py
flywheel_bids/flywheel_bids_app_toolkit/report.py
flywheel_bids/flywheel_bids_app_toolkit/tests/conftest.py
flywheel_bids/flywheel_bids_app_toolkit/tests/test_autoupdate.py
flywheel_bids/flywheel_bids_app_toolkit/tests/test_commands.py
flywheel_bids/flywheel_bids_app_toolkit/tests/test_compression.py
flywheel_bids/flywheel_bids_app_toolkit/tests/test_context.py
flywheel_bids/flywheel_bids_app_toolkit/tests/test_hpc_utils.py
flywheel_bids/flywheel_bids_app_toolkit/tests/test_old_run_level.py
flywheel_bids/flywheel_bids_app_toolkit/tests/test_prep.py
flywheel_bids/flywheel_bids_app_toolkit/tests/test_report.py
flywheel_bids/flywheel_bids_app_toolkit/tests/test_util_helpers.py
flywheel_bids/flywheel_bids_app_toolkit/tests/test_utils_query_flywheel.py
flywheel_bids/flywheel_bids_app_toolkit/tests/test_utils_tree.py
flywheel_bids/flywheel_bids_app_toolkit/utils/__init__.py
flywheel_bids/flywheel_bids_app_toolkit/utils/autoupdate_platform_test.py
flywheel_bids/flywheel_bids_app_toolkit/utils/helpers.py
flywheel_bids/flywheel_bids_app_toolkit/utils/performance.py
flywheel_bids/flywheel_bids_app_toolkit/utils/poetry_export.sh
flywheel_bids/flywheel_bids_app_toolkit/utils/query_flywheel.py
flywheel_bids/flywheel_bids_app_toolkit/utils/tree.py
flywheel_bids/supporting_files/__init__.py
flywheel_bids/supporting_files/bidsify_flywheel.py
flywheel_bids/supporting_files/classifications.py
flywheel_bids/supporting_files/errors.py
flywheel_bids-1.2.33.dist-info/METADATA
flywheel_bids-1.2.33.dist-info/WHEEL
flywheel_bids-1.2.33.dist-info/licenses/LICENSE
flywheel_bids-1.2.33.dist-info/RECORD
