Metadata-Version: 2.4
Name: flywheel-bids
Version: 1.2.33
Summary: Flywheel BIDS Client
Project-URL: Repository, https://gitlab.com/flywheel-io/public/bids-client
Author-email: Flywheel <support@flywheel.io>
License-Expression: MIT
License-File: LICENSE
Keywords: BIDS,Flywheel,SDK,flywheel
Classifier: Programming Language :: Python :: 3
Classifier: Programming Language :: Python :: 3.8
Classifier: Programming Language :: Python :: 3.9
Classifier: Programming Language :: Python :: 3.10
Classifier: Programming Language :: Python :: 3.11
Classifier: Programming Language :: Python :: 3.12
Classifier: Programming Language :: Python :: 3.13
Classifier: Programming Language :: Python :: 3.14
Classifier: Topic :: Scientific/Engineering
Requires-Python: <4,>=3.11
Requires-Dist: beautifulsoup4<5,>=4.12.2
Requires-Dist: flywheel-gear-toolkit<0.7,>=0.6
Requires-Dist: flywheel-sdk<21,>=20
Requires-Dist: importlib-resources<7,>=6.4.0
Requires-Dist: jsonschema<5,>=4.23.0
Requires-Dist: rtstatlib<2,>=1.0.0
Requires-Dist: six<2,>=1.17.0
Requires-Dist: urllib3<3,>=2.2.2
Provides-Extra: all
Requires-Dist: psutil<7,>=6.0.0; extra == 'all'
